neutron_dynamic_routing/__init__.py
neutron_dynamic_routing/_i18n.py
neutron_dynamic_routing/version.py
neutron_dynamic_routing/api/__init__.py
neutron_dynamic_routing/api/rpc/__init__.py
neutron_dynamic_routing/api/rpc/agentnotifiers/__init__.py
neutron_dynamic_routing/api/rpc/agentnotifiers/bgp_dr_rpc_agent_api.py
neutron_dynamic_routing/api/rpc/callbacks/__init__.py
neutron_dynamic_routing/api/rpc/callbacks/resources.py
neutron_dynamic_routing/api/rpc/handlers/__init__.py
neutron_dynamic_routing/api/rpc/handlers/bgp_speaker_rpc.py
neutron_dynamic_routing/cmd/__init__.py
neutron_dynamic_routing/cmd/eventlet/__init__.py
neutron_dynamic_routing/cmd/eventlet/agents/__init__.py
neutron_dynamic_routing/cmd/eventlet/agents/bgp_dragent.py
neutron_dynamic_routing/db/__init__.py
neutron_dynamic_routing/db/bgp_db.py
neutron_dynamic_routing/db/bgp_dragentscheduler_db.py
neutron_dynamic_routing/db/migration/README
neutron_dynamic_routing/db/migration/__init__.py
neutron_dynamic_routing/db/migration/alembic_migrations/__init__.py
neutron_dynamic_routing/db/migration/alembic_migrations/env.py
neutron_dynamic_routing/db/migration/alembic_migrations/script.py.mako
neutron_dynamic_routing/db/migration/alembic_migrations/versions/CONTRACT_HEAD
neutron_dynamic_routing/db/migration/alembic_migrations/versions/EXPAND_HEAD
neutron_dynamic_routing/db/migration/alembic_migrations/versions/start_neutron_dynamic_routing.py
neutron_dynamic_routing/db/migration/alembic_migrations/versions/newton/contract/4cf8bc3edb66_rename_tenant_to_project.py
neutron_dynamic_routing/db/migration/alembic_migrations/versions/newton/contract/61cc795e43e8_initial.py
neutron_dynamic_routing/db/migration/alembic_migrations/versions/newton/expand/f399fa0f5f25_initial.py
neutron_dynamic_routing/db/migration/alembic_migrations/versions/queens/contract/a589fdb5724c_change_size_of_as_number.py
neutron_dynamic_routing/db/migration/models/__init__.py
neutron_dynamic_routing/db/migration/models/head.py
neutron_dynamic_routing-27.0.0.dist-info/AUTHORS
neutron_dynamic_routing-27.0.0.dist-info/LICENSE
neutron_dynamic_routing-27.0.0.dist-info/METADATA
neutron_dynamic_routing-27.0.0.dist-info/WHEEL
neutron_dynamic_routing-27.0.0.dist-info/entry_points.txt
neutron_dynamic_routing-27.0.0.dist-info/pbr.json
neutron_dynamic_routing-27.0.0.dist-info/top_level.txt
neutron_dynamic_routing-27.0.0.dist-info/RECORD
